dtreg/__init__.py
dtreg/dtr_interface.py
dtreg/extract_epic.py
dtreg/extract_orkg.py
dtreg/from_static.py
dtreg/helpers.py
dtreg/load_datatype.py
dtreg/request_dtr.py
dtreg/to_jsonld.py
dtreg/data/ePIC-21-T11909-0424f6e7026fa4bc2c4a.json
dtreg/data/ePIC-21-T11909-1f20e66b17a6eb7c2baf.json
dtreg/data/ePIC-21-T11909-286991b26f02d58ee490.json
dtreg/data/ePIC-21-T11909-31483624b5c80014b6c7.json
dtreg/data/ePIC-21-T11909-37182ecfb4474942e255.json
dtreg/data/ePIC-21-T11909-3df63b7acb0522da685d.json
dtreg/data/ePIC-21-T11909-3f64a93eef69d721518f.json
dtreg/data/ePIC-21-T11909-437807f8d1a81b5138a3.json
dtreg/data/ePIC-21-T11909-4607bc7c42ac8db29bfc.json
dtreg/data/ePIC-21-T11909-4b99260369df9110f9bd.json
dtreg/data/ePIC-21-T11909-5b66cb584b974b186f37.json
dtreg/data/ePIC-21-T11909-5e782e67e70d0b2a022a.json
dtreg/data/ePIC-21-T11909-65ba00e95e60fb8971e6.json
dtreg/data/ePIC-21-T11909-6e3e29ce3ba5a0b9abfe.json
dtreg/data/ePIC-21-T11909-9bf7a8e8909bfd491b38.json
dtreg/data/ePIC-21-T11909-abef9f1c0d48853f3e51.json
dtreg/data/ePIC-21-T11909-aff130c76e68ead3862e.json
dtreg/data/ePIC-21-T11909-b9335ce2c99ed87735a6.json
dtreg/data/ePIC-21-T11909-c6b413ba96ba477b5dca.json
dtreg/data/ePIC-21-T11909-c6e19df3b52ab8d855a9.json
dtreg/data/ePIC-21-T11909-c981d125d1a564c9f573.json
dtreg/data/ePIC-21-T11909-cceac5fb8acf5ade2bf5.json
dtreg/data/ePIC-21-T11909-e0efc41346cda4ba84ca.json
dtreg/data/ePIC-21-T11909-fb2e379f820c6f8f9e82.json
dtreg-1.1.0.dist-info/LICENSE
dtreg-1.1.0.dist-info/METADATA
dtreg-1.1.0.dist-info/WHEEL
dtreg-1.1.0.dist-info/top_level.txt
dtreg-1.1.0.dist-info/RECORD
