Metadata-Version: 2.1
Name: dtreg
Version: 1.1.0
Summary: Interact with Data Type Registries and Create Machine Actionable Data
Author-email: Olga Lezhnina <olga.lezhnina@tib.eu>, Manuel Prinz <manuel.prinz@tib.eu>, Markus Stocker <markus.stocker@tib.eu>
Maintainer-email: Olga Lezhnina <olga.lezhnina@tib.eu>
License: MIT
Project-URL: Repository, https://gitlab.com/TIBHannover/orkg/dtreg-python
Project-URL: Changelog, https://gitlab.com/TIBHannover/orkg/dtreg-python/-/blob/master/CHANGELOG.md
Keywords: data type registry,schema,JSON-LD
Classifier: Intended Audience :: Science/Research
Classifier: Topic :: Scientific/Engineering
Classifier: Programming Language :: Python :: 3
Classifier: License :: OSI Approved :: MIT License
Requires-Python: >=3.8
License-File: LICENSE
Requires-Dist: importlib_resources
Requires-Dist: pandas
Requires-Dist: requests
